explosion_distance_estimator/__init__.py
explosion_distance_estimator/audio_utils.py
explosion_distance_estimator/config.py
explosion_distance_estimator/estimation.py
explosion_distance_estimator/explosion_distance_estimator.py
explosion_distance_estimator/log_utils.py
explosion_distance_estimator/plotting.py
explosion_distance_estimator/weather.py
explosion_distance_estimator/video/__init__.py
explosion_distance_estimator/video/detect_flash.py
explosion_distance_estimator/video/extract.py
explosion_distance_estimator-1.0.7.dist-info/LICENSE
explosion_distance_estimator-1.0.7.dist-info/METADATA
explosion_distance_estimator-1.0.7.dist-info/WHEEL
explosion_distance_estimator-1.0.7.dist-info/entry_points.txt
explosion_distance_estimator-1.0.7.dist-info/top_level.txt
explosion_distance_estimator-1.0.7.dist-info/RECORD
